setup.py
cloudplaya/__init__.py
cloudplaya/album.py
cloudplaya/artist.py
cloudplaya/client.py
cloudplaya/main.py
cloudplaya/song.py
cloudplaya.egg-info/PKG-INFO
cloudplaya.egg-info/SOURCES.txt
cloudplaya.egg-info/dependency_links.txt
cloudplaya.egg-info/entry_points.txt
cloudplaya.egg-info/requires.txt
cloudplaya.egg-info/top_level.txt