Metadata-Version: 1.0
Name: cloudplaya
Version: 0.1
Summary: Python module and command line client for Amazon Cloud Player
Home-page: http://github.com/chipx86/cloudplaya/
Author: Christian Hammond
Author-email: chipx86@chipx86.com
License: MIT
Platform: UNKNOWN
Classifier: Development Status :: 4 - Beta
Classifier: Environment :: Console
Classifier: Intended Audience :: Developers
Classifier: License :: OSI Approved :: MIT License
Classifier: Operating System :: OS Independent
Classifier: Programming Language :: Python
Classifier: Topic :: Software Development
